{"id":"e4bb6261-d901-400c-9644-9a8e659be02c","timestamp":1712886590475,"matcher":{"static":{"/api/search":{"prerender":true}},"wildcard":{},"dynamic":{}},"prerendered":["/","/guide","/guide/enterprise","/guide/nuxt","/guide/migration","/components","/components/challenge-v3","/composables/challenge-v2","/guide/faq","/components/challenge-v2","/composables/recaptcha-provider","/integration/vee-validation","/composables/challenge-v3","/advanced/customize-recaptcha-script-loading","/components/checkbox"]}